dataporten/__init__.py
dataporten/admin.py
dataporten/api.py
dataporten/apps.py
dataporten/middleware.py
dataporten/models.py
dataporten/parsers.py
dataporten/settings.py
dataporten/views.py
dataporten/migrations/0001_initial.py
dataporten/migrations/__init__.py
dataporten/tests/__init__.py
dataporten/tests/conftest.py
dataporten/tests/factories.py
dataporten/tests/test_api.py
dataporten/tests/test_middleware.py
dataporten/tests/test_models.py
dataporten/tests/test_parsers.py
dataporten/tests/utils.py
django_dataporten-0.4.0.dist-info/LICENSE
django_dataporten-0.4.0.dist-info/METADATA
django_dataporten-0.4.0.dist-info/WHEEL
django_dataporten-0.4.0.dist-info/top_level.txt
django_dataporten-0.4.0.dist-info/RECORD
