Metadata-Version: 2.1
Name: django-dataporten
Version: 0.4.0
Summary: A simple Django app to fetch and parse data from Dataporten.
Home-page: https://github.com/JakobGM/django-dataporten
Author: Jakob Gerhard Martinussen
Author-email: jakobgm@gmail.com
License: MIT License
Platform: UNKNOWN
Classifier: Environment :: Web Environment
Classifier: Framework :: Django
Classifier: Framework :: Django :: 1.11
Classifier: Framework :: Django :: 2.0
Classifier: Framework :: Django :: 2.1
Classifier: Intended Audience :: Developers
Classifier: License :: OSI Approved :: MIT License
Classifier: Operating System :: OS Independent
Classifier: Programming Language :: Python
Classifier: Programming Language :: Python :: 3
Classifier: Programming Language :: Python :: 3.6
Classifier: Programming Language :: Python :: 3.7
Classifier: Topic :: Internet :: WWW/HTTP
Classifier: Topic :: Internet :: WWW/HTTP :: WSGI :: Middleware
Requires-Dist: django
Requires-Dist: pip-tools
Requires-Dist: pytest
Requires-Dist: pytest-django
Requires-Dist: requests
Requires-Dist: requests-cache
Requires-Dist: responses
Requires-Dist: mypy
Requires-Dist: mypy-extensions
Requires-Dist: freezegun
Requires-Dist: factory-boy
Requires-Dist: django-allauth
